paxpar/cli/__main__.py
paxpar/cli/pp.py
paxpar/cli/tools.py
paxpar/cli/command/build.py
paxpar/cli/command/conf.py
paxpar/cli/command/deploy.py
paxpar/cli/command/dev.py
paxpar/cli/command/image.py
paxpar/cli/command/misc.py
paxpar/cli/command/py.py
paxpar/cli/command/ref.py
paxpar/cli/command/run.py
paxpar/cli/command/s3.py
paxpar/cli/command/scrap.py
paxpar/cli/command/setup.py
paxpar/cli/command/status.py
paxpar/cli/command/test.py
paxpar/cli/command/version.py
paxpar_cli-4.4.49.dist-info/METADATA
paxpar_cli-4.4.49.dist-info/WHEEL
paxpar_cli-4.4.49.dist-info/entry_points.txt
paxpar_cli-4.4.49.dist-info/RECORD
